cmip/__init__.py
cmip/utils.py
cmip/data/ad.txt
cmip/data/chinese_frequency.tsv
cmip/data/letter_mapping.txt
cmip/data/pinyin.txt
cmip/gibberish/__init__.py
cmip/gibberish/gibberish.py
cmip/image/__init__.py
cmip/text/__init__.py
cmip/text/ac_automation.py
cmip/text/encoder.py
cmip/text/normalize.py
cmip/text/prefix_set.py
cmip/text/similarity.py
cmip/web/__init__.py
cmip/web/fetch_html.py
cmip/web/html.py
cmip/web/simhash_utils.py
cmip/web/utils.py
cmip/web/web_scraping.py
cmip/web/web_scraping2.py
cmip/word_discover/__init__.py
cmip/word_discover/ngram.py
cmip/word_discover/word_discover.py
test/__init__.py
test/test_ac_automation.py
cmip-0.0.9.dist-info/LICENSE
cmip-0.0.9.dist-info/METADATA
cmip-0.0.9.dist-info/WHEEL
cmip-0.0.9.dist-info/top_level.txt
cmip-0.0.9.dist-info/RECORD
