Metadata-Version: 2.1
Name: cmip
Version: 0.0.9
Summary: An efficient information processing program.
Home-page: https://github.com/mikuh/cmip
Author: geb
Author-email: 853934146@qq.com
Classifier: Programming Language :: Python :: 3
Classifier: Operating System :: OS Independent
Requires-Python: >=3.8
License-File: LICENSE
Requires-Dist: numpy
Requires-Dist: pandas
Requires-Dist: nltk
Requires-Dist: validators
